MANIFEST.in
README.md
setup.py
dash_smoothie/Smoothie.py
dash_smoothie/__init__.py
dash_smoothie/_imports_.py
dash_smoothie/dash_smoothie.dev.js
dash_smoothie/dash_smoothie.min.js
dash_smoothie/metadata.json
dash_smoothie/package.json
dash_smoothie.egg-info/PKG-INFO
dash_smoothie.egg-info/SOURCES.txt
dash_smoothie.egg-info/dependency_links.txt
dash_smoothie.egg-info/top_level.txt