Metadata-Version: 1.0
Name: dash-smoothie
Version: 0.0.1
Summary: Realtime dash component
Home-page: UNKNOWN
Author: Harpo harpo@harpo.me
Author-email: UNKNOWN
License: MIT
Platform: UNKNOWN
